{
	"animations": [
		{
			"loop": false,
			"offsets": [
				-40,
				0
			],
			"anim": "idle",
			"fps": 24,
			"name": "idle",
			"indices": []
		},
		{
			"loop": false,
			"offsets": [
				44,
				-3
			],
			"anim": "singLEFT",
			"fps": 24,
			"name": "left",
			"indices": []
		},
		{
			"loop": false,
			"offsets": [
				-68,
				-5
			],
			"anim": "singDOWN",
			"fps": 24,
			"name": "down",
			"indices": []
		},
		{
			"loop": false,
			"offsets": [
				-6,
				32
			],
			"anim": "singUP",
			"fps": 24,
			"name": "up",
			"indices": []
		},
		{
			"loop": false,
			"offsets": [
				-62,
				-7
			],
			"anim": "singRIGHT",
			"fps": 24,
			"name": "right",
			"indices": []
		}
	],
	"no_antialiasing": false,
	"image": "characters/invis",
	"position": [
		0,
		320
	],
	"healthbar_colors2": [
		91,
		167,
		219
	],
	"healthicon": "bf",
	"flip_x": false,
	"healthbar_colors": [
		91,
		167,
		219
	],
	"camera_position": [
		720,
		490
	],
	"sing_duration": 6.1,
	"scale": 1
}